PokemonLmba/__init__.py
PokemonLmba/pokemon.csv
PokemonLmba/random_pokemon.py
Pokemon_Library-Lmba/__init__.py
Pokemon_Library-Lmba/pokemon.csv
Pokemon_Library-Lmba/random_pokemon.py
PokemonLmba-1.0.0.dist-info/METADATA
PokemonLmba-1.0.0.dist-info/WHEEL
PokemonLmba-1.0.0.dist-info/top_level.txt
PokemonLmba-1.0.0.dist-info/RECORD
