Metadata-Version: 2.1
Name: PokemonLmba
Version: 1.0.0
Summary: Libreria para generar un pokemon aleatorio.
Author: Litzy Barrera
Author-email: 202224128_barrera@tesch.edu.mx
Requires-Dist: pandas
